ebin_ai_assistant/__init__.py
ebin_ai_assistant/core.py
ebin_ai_assistant-1.0.6.dist-info/METADATA
ebin_ai_assistant-1.0.6.dist-info/WHEEL
ebin_ai_assistant-1.0.6.dist-info/top_level.txt
ebin_ai_assistant-1.0.6.dist-info/RECORD
