Metadata-Version: 2.4
Name: ebin_ai_assistant
Version: 1.0.6
Summary: A library containing AI utility functions
Author-email: Ebin Louis <ebinlouis1559@gmail.com>
Project-URL: Homepage, https://github.com/pypa/sampleproject
Project-URL: Bug Tracker, https://github.com/pypa/sampleproject/issues
Classifier: Programming Language :: Python :: 3
Classifier: License :: OSI Approved :: MIT License
Classifier: Operating System :: OS Independent
Requires-Python: >=3.9
Requires-Dist: google-generativeai
